Seq2SeqSharp/AdvUtils.dll
Seq2SeqSharp/AdvUtils.pdb
Seq2SeqSharp/CudaBlas.dll
Seq2SeqSharp/CudaBlas.pdb
Seq2SeqSharp/CudaRand.dll
Seq2SeqSharp/CudaRand.pdb
Seq2SeqSharp/GPTConsole.deps.json
Seq2SeqSharp/GPTConsole.dll
Seq2SeqSharp/GPTConsole.pdb
Seq2SeqSharp/GPTConsole.runtimeconfig.json
Seq2SeqSharp/InitDevices.py
Seq2SeqSharp/ManagedCuda.dll
Seq2SeqSharp/ManagedCuda.pdb
Seq2SeqSharp/Microsoft.Extensions.Caching.Abstractions.dll
Seq2SeqSharp/Microsoft.Extensions.Caching.Memory.dll
Seq2SeqSharp/Microsoft.Extensions.DependencyInjection.Abstractions.dll
Seq2SeqSharp/Microsoft.Extensions.Logging.Abstractions.dll
Seq2SeqSharp/Microsoft.Extensions.Options.dll
Seq2SeqSharp/Microsoft.Extensions.Primitives.dll
Seq2SeqSharp/NVRTC.dll
Seq2SeqSharp/NVRTC.pdb
Seq2SeqSharp/Newtonsoft.Json.dll
Seq2SeqSharp/Seq2SeqConsole.deps.json
Seq2SeqSharp/Seq2SeqConsole.dll
Seq2SeqSharp/Seq2SeqConsole.dll.config
Seq2SeqSharp/Seq2SeqConsole.pdb
Seq2SeqSharp/Seq2SeqConsole.runtimeconfig.json
Seq2SeqSharp/Seq2SeqSharp.dll
Seq2SeqSharp/Seq2SeqSharp.dll.config
Seq2SeqSharp/Seq2SeqSharp.pdb
Seq2SeqSharp/TensorSharp.CUDA.dll
Seq2SeqSharp/TensorSharp.CUDA.dll.config
Seq2SeqSharp/TensorSharp.CUDA.pdb
Seq2SeqSharp/TensorSharp.dll
Seq2SeqSharp/TensorSharp.pdb
Seq2SeqSharp/__init__.py
Seq2SeqSharp/protobuf-net.Core.dll
Seq2SeqSharp/protobuf-net.dll
Seq2SeqSharp-2.8.17.data/data/Seq2SeqSharp/AdvUtils.dll
Seq2SeqSharp-2.8.17.data/data/Seq2SeqSharp/AdvUtils.pdb
Seq2SeqSharp-2.8.17.data/data/Seq2SeqSharp/CudaBlas.dll
Seq2SeqSharp-2.8.17.data/data/Seq2SeqSharp/CudaBlas.pdb
Seq2SeqSharp-2.8.17.data/data/Seq2SeqSharp/CudaRand.dll
Seq2SeqSharp-2.8.17.data/data/Seq2SeqSharp/CudaRand.pdb
Seq2SeqSharp-2.8.17.data/data/Seq2SeqSharp/GPTConsole.deps.json
Seq2SeqSharp-2.8.17.data/data/Seq2SeqSharp/GPTConsole.dll
Seq2SeqSharp-2.8.17.data/data/Seq2SeqSharp/GPTConsole.pdb
Seq2SeqSharp-2.8.17.data/data/Seq2SeqSharp/GPTConsole.runtimeconfig.json
Seq2SeqSharp-2.8.17.data/data/Seq2SeqSharp/ManagedCuda.dll
Seq2SeqSharp-2.8.17.dist-info/LICENSE
Seq2SeqSharp-2.8.17.dist-info/METADATA
Seq2SeqSharp-2.8.17.dist-info/WHEEL
Seq2SeqSharp-2.8.17.dist-info/top_level.txt
Seq2SeqSharp-2.8.17.dist-info/RECORD
